{
    "UserVMs": [
        {
            "id": "v0",
            "vmType": "gp1",
            "bid": 112,
            "v_storage": 5587,
            "v_CPU": 8730,
            "v_RAM": 8504
        },
        {
            "id": "v1",
            "vmType": "gp1",
            "bid": 94,
            "v_storage": 6024,
            "v_CPU": 9454,
            "v_RAM": 7468
        },
        {
            "id": "v2",
            "vmType": "gp1",
            "bid": 106,
            "v_storage": 6158,
            "v_CPU": 7494,
            "v_RAM": 9316
        },
        {
            "id": "v3",
            "vmType": "gp1",
            "bid": 98,
            "v_storage": 6851,
            "v_CPU": 7325,
            "v_RAM": 9311
        },
        {
            "id": "v4",
            "vmType": "gp1",
            "bid": 87,
            "v_storage": 6339,
            "v_CPU": 8412,
            "v_RAM": 8795
        },
        {
            "id": "v5",
            "vmType": "gp1",
            "bid": 104,
            "v_storage": 6226,
            "v_CPU": 8593,
            "v_RAM": 8532
        },
        {
            "id": "v6",
            "vmType": "gp1",
            "bid": 115,
            "v_storage": 6455,
            "v_CPU": 8835,
            "v_RAM": 8894
        },
        {
            "id": "v7",
            "vmType": "gp1",
            "bid": 105,
            "v_storage": 5725,
            "v_CPU": 8310,
            "v_RAM": 8396
        },
        {
            "id": "v8",
            "vmType": "gp1",
            "bid": 106,
            "v_storage": 5434,
            "v_CPU": 9103,
            "v_RAM": 9255
        },
        {
            "id": "v9",
            "vmType": "gp1",
            "bid": 94,
            "v_storage": 7222,
            "v_CPU": 7929,
            "v_RAM": 8541
        },
        {
            "id": "v10",
            "vmType": "gp1",
            "bid": 109,
            "v_storage": 4606,
            "v_CPU": 6819,
            "v_RAM": 9862
        },
        {
            "id": "v11",
            "vmType": "gp1",
            "bid": 93,
            "v_storage": 6521,
            "v_CPU": 8761,
            "v_RAM": 8402
        },
        {
            "id": "v12",
            "vmType": "gp1",
            "bid": 92,
            "v_storage": 6576,
            "v_CPU": 8272,
            "v_RAM": 7852
        },
        {
            "id": "v13",
            "vmType": "gp1",
            "bid": 88,
            "v_storage": 6066,
            "v_CPU": 8529,
            "v_RAM": 8639
        },
        {
            "id": "v14",
            "vmType": "gp1",
            "bid": 107,
            "v_storage": 5255,
            "v_CPU": 8571,
            "v_RAM": 6852
        },
        {
            "id": "v15",
            "vmType": "gp1",
            "bid": 86,
            "v_storage": 7603,
            "v_CPU": 7586,
            "v_RAM": 7476
        },
        {
            "id": "v16",
            "vmType": "gp1",
            "bid": 112,
            "v_storage": 6432,
            "v_CPU": 7568,
            "v_RAM": 8051
        },
        {
            "id": "v17",
            "vmType": "gp1",
            "bid": 96,
            "v_storage": 6913,
            "v_CPU": 6193,
            "v_RAM": 8120
        },
        {
            "id": "v18",
            "vmType": "gp1",
            "bid": 102,
            "v_storage": 5662,
            "v_CPU": 9495,
            "v_RAM": 7586
        },
        {
            "id": "v19",
            "vmType": "gp1",
            "bid": 93,
            "v_storage": 6051,
            "v_CPU": 8052,
            "v_RAM": 7990
        },
        {
            "id": "v20",
            "vmType": "gp2",
            "bid": 111,
            "v_storage": 29241,
            "v_CPU": 17024,
            "v_RAM": 36088
        },
        {
            "id": "v21",
            "vmType": "gp2",
            "bid": 101,
            "v_storage": 25980,
            "v_CPU": 16482,
            "v_RAM": 37815
        },
        {
            "id": "v22",
            "vmType": "gp2",
            "bid": 112,
            "v_storage": 30073,
            "v_CPU": 16001,
            "v_RAM": 30512
        },
        {
            "id": "v23",
            "vmType": "gp2",
            "bid": 77,
            "v_storage": 38202,
            "v_CPU": 16056,
            "v_RAM": 37543
        },
        {
            "id": "v24",
            "vmType": "gp2",
            "bid": 106,
            "v_storage": 30096,
            "v_CPU": 17636,
            "v_RAM": 26117
        },
        {
            "id": "v25",
            "vmType": "gp2",
            "bid": 101,
            "v_storage": 28844,
            "v_CPU": 16461,
            "v_RAM": 36388
        },
        {
            "id": "v26",
            "vmType": "gp2",
            "bid": 89,
            "v_storage": 31142,
            "v_CPU": 17565,
            "v_RAM": 32962
        },
        {
            "id": "v27",
            "vmType": "gp2",
            "bid": 123,
            "v_storage": 35964,
            "v_CPU": 13684,
            "v_RAM": 36731
        },
        {
            "id": "v28",
            "vmType": "gp2",
            "bid": 105,
            "v_storage": 30157,
            "v_CPU": 15733,
            "v_RAM": 32732
        },
        {
            "id": "v29",
            "vmType": "gp2",
            "bid": 113,
            "v_storage": 29568,
            "v_CPU": 15808,
            "v_RAM": 35330
        },
        {
            "id": "v30",
            "vmType": "gp2",
            "bid": 93,
            "v_storage": 29350,
            "v_CPU": 13924,
            "v_RAM": 36676
        },
        {
            "id": "v31",
            "vmType": "gp2",
            "bid": 112,
            "v_storage": 33908,
            "v_CPU": 16772,
            "v_RAM": 40792
        },
        {
            "id": "v32",
            "vmType": "gp2",
            "bid": 110,
            "v_storage": 32875,
            "v_CPU": 17803,
            "v_RAM": 34177
        },
        {
            "id": "v33",
            "vmType": "gp2",
            "bid": 99,
            "v_storage": 33035,
            "v_CPU": 16244,
            "v_RAM": 35022
        },
        {
            "id": "v34",
            "vmType": "gp2",
            "bid": 119,
            "v_storage": 34142,
            "v_CPU": 19235,
            "v_RAM": 33631
        },
        {
            "id": "v35",
            "vmType": "gp2",
            "bid": 113,
            "v_storage": 31399,
            "v_CPU": 16194,
            "v_RAM": 25219
        },
        {
            "id": "v36",
            "vmType": "gp2",
            "bid": 90,
            "v_storage": 26730,
            "v_CPU": 15727,
            "v_RAM": 36166
        },
        {
            "id": "v37",
            "vmType": "gp2",
            "bid": 87,
            "v_storage": 34080,
            "v_CPU": 18805,
            "v_RAM": 33578
        },
        {
            "id": "v38",
            "vmType": "gp2",
            "bid": 117,
            "v_storage": 37518,
            "v_CPU": 17836,
            "v_RAM": 31060
        },
        {
            "id": "v39",
            "vmType": "gp2",
            "bid": 98,
            "v_storage": 27596,
            "v_CPU": 16327,
            "v_RAM": 39581
        },
        {
            "id": "v40",
            "vmType": "ramInt",
            "bid": 145,
            "v_storage": 33121,
            "v_CPU": 29454,
            "v_RAM": 143533
        },
        {
            "id": "v41",
            "vmType": "ramInt",
            "bid": 151,
            "v_storage": 30697,
            "v_CPU": 33580,
            "v_RAM": 131251
        },
        {
            "id": "v42",
            "vmType": "ramInt",
            "bid": 157,
            "v_storage": 35541,
            "v_CPU": 29322,
            "v_RAM": 132347
        },
        {
            "id": "v43",
            "vmType": "ramInt",
            "bid": 150,
            "v_storage": 30334,
            "v_CPU": 30688,
            "v_RAM": 146474
        },
        {
            "id": "v44",
            "vmType": "ramInt",
            "bid": 146,
            "v_storage": 32679,
            "v_CPU": 31467,
            "v_RAM": 128476
        },
        {
            "id": "v45",
            "vmType": "ramInt",
            "bid": 142,
            "v_storage": 27867,
            "v_CPU": 31203,
            "v_RAM": 130585
        },
        {
            "id": "v46",
            "vmType": "ramInt",
            "bid": 143,
            "v_storage": 39202,
            "v_CPU": 29092,
            "v_RAM": 113798
        },
        {
            "id": "v47",
            "vmType": "ramInt",
            "bid": 137,
            "v_storage": 28144,
            "v_CPU": 30711,
            "v_RAM": 134856
        },
        {
            "id": "v48",
            "vmType": "ramInt",
            "bid": 154,
            "v_storage": 34360,
            "v_CPU": 31730,
            "v_RAM": 136105
        },
        {
            "id": "v49",
            "vmType": "ramInt",
            "bid": 147,
            "v_storage": 37962,
            "v_CPU": 32218,
            "v_RAM": 119894
        },
        {
            "id": "v50",
            "vmType": "ramInt",
            "bid": 147,
            "v_storage": 30790,
            "v_CPU": 35114,
            "v_RAM": 122333
        },
        {
            "id": "v51",
            "vmType": "ramInt",
            "bid": 151,
            "v_storage": 34823,
            "v_CPU": 34515,
            "v_RAM": 129707
        },
        {
            "id": "v52",
            "vmType": "ramInt",
            "bid": 147,
            "v_storage": 33486,
            "v_CPU": 27098,
            "v_RAM": 124168
        },
        {
            "id": "v53",
            "vmType": "ramInt",
            "bid": 144,
            "v_storage": 29063,
            "v_CPU": 31695,
            "v_RAM": 124495
        },
        {
            "id": "v54",
            "vmType": "ramInt",
            "bid": 144,
            "v_storage": 31272,
            "v_CPU": 31252,
            "v_RAM": 130086
        },
        {
            "id": "v55",
            "vmType": "ramInt",
            "bid": 166,
            "v_storage": 28827,
            "v_CPU": 29594,
            "v_RAM": 148047
        },
        {
            "id": "v56",
            "vmType": "ramInt",
            "bid": 147,
            "v_storage": 41117,
            "v_CPU": 32475,
            "v_RAM": 134452
        },
        {
            "id": "v57",
            "vmType": "ramInt",
            "bid": 132,
            "v_storage": 33432,
            "v_CPU": 32551,
            "v_RAM": 144078
        },
        {
            "id": "v58",
            "vmType": "ramInt",
            "bid": 156,
            "v_storage": 35116,
            "v_CPU": 34678,
            "v_RAM": 123283
        },
        {
            "id": "v59",
            "vmType": "ramInt",
            "bid": 149,
            "v_storage": 32393,
            "v_CPU": 31974,
            "v_RAM": 111776
        },
        {
            "id": "v60",
            "vmType": "cpuInt",
            "bid": 147,
            "v_storage": 34598,
            "v_CPU": 63071,
            "v_RAM": 66485
        },
        {
            "id": "v61",
            "vmType": "cpuInt",
            "bid": 166,
            "v_storage": 30746,
            "v_CPU": 67226,
            "v_RAM": 63000
        },
        {
            "id": "v62",
            "vmType": "cpuInt",
            "bid": 153,
            "v_storage": 37667,
            "v_CPU": 58799,
            "v_RAM": 58715
        },
        {
            "id": "v63",
            "vmType": "cpuInt",
            "bid": 153,
            "v_storage": 34684,
            "v_CPU": 65021,
            "v_RAM": 60775
        },
        {
            "id": "v64",
            "vmType": "cpuInt",
            "bid": 156,
            "v_storage": 28884,
            "v_CPU": 67269,
            "v_RAM": 58521
        },
        {
            "id": "v65",
            "vmType": "cpuInt",
            "bid": 138,
            "v_storage": 31694,
            "v_CPU": 59902,
            "v_RAM": 56866
        },
        {
            "id": "v66",
            "vmType": "cpuInt",
            "bid": 155,
            "v_storage": 36546,
            "v_CPU": 70304,
            "v_RAM": 56798
        },
        {
            "id": "v67",
            "vmType": "cpuInt",
            "bid": 140,
            "v_storage": 31861,
            "v_CPU": 58270,
            "v_RAM": 61637
        },
        {
            "id": "v68",
            "vmType": "cpuInt",
            "bid": 151,
            "v_storage": 29186,
            "v_CPU": 67573,
            "v_RAM": 72970
        },
        {
            "id": "v69",
            "vmType": "cpuInt",
            "bid": 150,
            "v_storage": 27345,
            "v_CPU": 62143,
            "v_RAM": 63209
        },
        {
            "id": "v70",
            "vmType": "cpuInt",
            "bid": 144,
            "v_storage": 35258,
            "v_CPU": 63540,
            "v_RAM": 47936
        },
        {
            "id": "v71",
            "vmType": "cpuInt",
            "bid": 153,
            "v_storage": 35673,
            "v_CPU": 61853,
            "v_RAM": 78527
        },
        {
            "id": "v72",
            "vmType": "cpuInt",
            "bid": 158,
            "v_storage": 34473,
            "v_CPU": 62218,
            "v_RAM": 59438
        },
        {
            "id": "v73",
            "vmType": "cpuInt",
            "bid": 143,
            "v_storage": 36951,
            "v_CPU": 66211,
            "v_RAM": 70798
        },
        {
            "id": "v74",
            "vmType": "cpuInt",
            "bid": 139,
            "v_storage": 38116,
            "v_CPU": 57809,
            "v_RAM": 65525
        },
        {
            "id": "v75",
            "vmType": "cpuInt",
            "bid": 131,
            "v_storage": 38567,
            "v_CPU": 58522,
            "v_RAM": 59089
        },
        {
            "id": "v76",
            "vmType": "cpuInt",
            "bid": 127,
            "v_storage": 30815,
            "v_CPU": 58562,
            "v_RAM": 66374
        },
        {
            "id": "v77",
            "vmType": "cpuInt",
            "bid": 147,
            "v_storage": 33598,
            "v_CPU": 71154,
            "v_RAM": 69273
        },
        {
            "id": "v78",
            "vmType": "cpuInt",
            "bid": 143,
            "v_storage": 35130,
            "v_CPU": 68915,
            "v_RAM": 70184
        },
        {
            "id": "v79",
            "vmType": "cpuInt",
            "bid": 155,
            "v_storage": 34938,
            "v_CPU": 69803,
            "v_RAM": 61062
        },
        {
            "id": "v80",
            "vmType": "extra",
            "bid": 191,
            "v_storage": 68567,
            "v_CPU": 129299,
            "v_RAM": 255425
        },
        {
            "id": "v81",
            "vmType": "extra",
            "bid": 200,
            "v_storage": 61740,
            "v_CPU": 129836,
            "v_RAM": 253987
        },
        {
            "id": "v82",
            "vmType": "extra",
            "bid": 189,
            "v_storage": 67515,
            "v_CPU": 142601,
            "v_RAM": 290065
        },
        {
            "id": "v83",
            "vmType": "extra",
            "bid": 189,
            "v_storage": 68300,
            "v_CPU": 130161,
            "v_RAM": 278547
        },
        {
            "id": "v84",
            "vmType": "extra",
            "bid": 199,
            "v_storage": 66845,
            "v_CPU": 136983,
            "v_RAM": 278112
        },
        {
            "id": "v85",
            "vmType": "extra",
            "bid": 192,
            "v_storage": 64177,
            "v_CPU": 129075,
            "v_RAM": 261879
        },
        {
            "id": "v86",
            "vmType": "extra",
            "bid": 198,
            "v_storage": 64843,
            "v_CPU": 129079,
            "v_RAM": 264784
        },
        {
            "id": "v87",
            "vmType": "extra",
            "bid": 194,
            "v_storage": 65492,
            "v_CPU": 129012,
            "v_RAM": 261746
        },
        {
            "id": "v88",
            "vmType": "extra",
            "bid": 212,
            "v_storage": 65305,
            "v_CPU": 132794,
            "v_RAM": 261273
        },
        {
            "id": "v89",
            "vmType": "extra",
            "bid": 199,
            "v_storage": 62809,
            "v_CPU": 123410,
            "v_RAM": 256685
        },
        {
            "id": "v90",
            "vmType": "extra",
            "bid": 197,
            "v_storage": 65909,
            "v_CPU": 139066,
            "v_RAM": 269433
        },
        {
            "id": "v91",
            "vmType": "extra",
            "bid": 206,
            "v_storage": 63717,
            "v_CPU": 122108,
            "v_RAM": 253635
        },
        {
            "id": "v92",
            "vmType": "extra",
            "bid": 208,
            "v_storage": 65644,
            "v_CPU": 120728,
            "v_RAM": 269359
        },
        {
            "id": "v93",
            "vmType": "extra",
            "bid": 198,
            "v_storage": 68504,
            "v_CPU": 137410,
            "v_RAM": 273184
        },
        {
            "id": "v94",
            "vmType": "extra",
            "bid": 193,
            "v_storage": 69640,
            "v_CPU": 130353,
            "v_RAM": 253288
        },
        {
            "id": "v95",
            "vmType": "extra",
            "bid": 196,
            "v_storage": 66259,
            "v_CPU": 121278,
            "v_RAM": 247521
        },
        {
            "id": "v96",
            "vmType": "extra",
            "bid": 188,
            "v_storage": 67984,
            "v_CPU": 126880,
            "v_RAM": 267913
        },
        {
            "id": "v97",
            "vmType": "extra",
            "bid": 191,
            "v_storage": 65255,
            "v_CPU": 136504,
            "v_RAM": 229041
        },
        {
            "id": "v98",
            "vmType": "extra",
            "bid": 195,
            "v_storage": 64874,
            "v_CPU": 121495,
            "v_RAM": 254624
        },
        {
            "id": "v99",
            "vmType": "extra",
            "bid": 186,
            "v_storage": 63759,
            "v_CPU": 126231,
            "v_RAM": 245386
        }
    ],
    "Cloudlets": [
        {
            "id": "cE_0",
            "c_storage": 8192000,
            "c_CPU": 240000,
            "c_RAM": 1048576
        },
        {
            "id": "cE_1",
            "c_storage": 8192000,
            "c_CPU": 240000,
            "c_RAM": 1048576
        },
        {
            "id": "cE_2",
            "c_storage": 8192000,
            "c_CPU": 240000,
            "c_RAM": 1048576
        },
        {
            "id": "cE_3",
            "c_storage": 8192000,
            "c_CPU": 240000,
            "c_RAM": 1048576
        },
        {
            "id": "cE_4",
            "c_storage": 8192000,
            "c_CPU": 240000,
            "c_RAM": 1048576
        },
        {
            "id": "cE_5",
            "c_storage": 8192000,
            "c_CPU": 240000,
            "c_RAM": 1048576
        },
        {
            "id": "cE_6",
            "c_storage": 8192000,
            "c_CPU": 240000,
            "c_RAM": 1048576
        },
        {
            "id": "cE_7",
            "c_storage": 8192000,
            "c_CPU": 240000,
            "c_RAM": 1048576
        },
        {
            "id": "cE_8",
            "c_storage": 8192000,
            "c_CPU": 240000,
            "c_RAM": 1048576
        },
        {
            "id": "cE_9",
            "c_storage": 8192000,
            "c_CPU": 240000,
            "c_RAM": 1048576
        }
    ]
}